hdistill/__init__.py
hdistill/command_handler.py
hdistill/main.py
hdistill/adapters/__init__.py
hdistill/adapters/http_client.py
hdistill/pipeline/__init__.py
hdistill/pipeline/handlers.py
hdistill/pipeline/html_parser.py
hdistill/pipeline/loader.py
hdistill/pipeline/sanitizer.py
hdistill/pipeline/transformer.py
tests/__init__.py
tests/test_html_parser.py
tests/test_sanitizer.py
tests/test_transformer.py
hdistill-1.0.0.dist-info/LICENSE
hdistill-1.0.0.dist-info/METADATA
hdistill-1.0.0.dist-info/WHEEL
hdistill-1.0.0.dist-info/entry_points.txt
hdistill-1.0.0.dist-info/top_level.txt
hdistill-1.0.0.dist-info/RECORD
