Metadata-Version: 2.1
Name: hdistill
Version: 1.0.0
Summary: CLI tool for parsing HTML
Home-page: https://github.com/SethTales/hdistill
Author: Seth Taylor
Author-email: seth.tales@gmail.com
License: MIT
Keywords: HTML parsing web-scraping
Platform: UNKNOWN
Classifier: Programming Language :: Python :: 3
Classifier: License :: OSI Approved :: MIT License
Classifier: Operating System :: OS Independent
Requires-Dist: lxml
